Metadata-Version: 1.0
Name: simplegeneric
Version: 0.7
Summary: Simple generic functions (similar to Python's own len(), pickle.dump(), etc.)
Home-page: http://cheeseshop.python.org/pypi/simplegeneric
Author: Phillip J. Eby
Author-email: peak@eby-sarna.com
License: http://www.apache.org/licenses/LICENSE-2.0
Platform: UNKNOWN
